mkdocs_diff_file_import/__init__.py
mkdocs_diff_file_import/diff_file_import.py
mkdocs_diff_file_import-0.1.6.dist-info/LICENSE
mkdocs_diff_file_import-0.1.6.dist-info/METADATA
mkdocs_diff_file_import-0.1.6.dist-info/WHEEL
mkdocs_diff_file_import-0.1.6.dist-info/entry_points.txt
mkdocs_diff_file_import-0.1.6.dist-info/RECORD
