Metadata-Version: 2.1
Name: mkdocs-diff-file-import
Version: 0.1.6
Summary: Import a diff file as MkDocs code block
Author: Francesco Lombardo
Requires-Python: >=3.7,<4.0
Classifier: Programming Language :: Python :: 3
Classifier: Programming Language :: Python :: 3.7
Classifier: Programming Language :: Python :: 3.8
Classifier: Programming Language :: Python :: 3.9
Classifier: Programming Language :: Python :: 3.10
Classifier: Programming Language :: Python :: 3.11
Requires-Dist: mkdocs (>=1.5.3,<2.0.0)
